sql/__init__.py
sql/column_guesser.py
sql/connection.py
sql/magic.py
sql/parse.py
sql/run.py
ipython_sql-0.5.0.dist-info/LICENSE
ipython_sql-0.5.0.dist-info/METADATA
ipython_sql-0.5.0.dist-info/WHEEL
ipython_sql-0.5.0.dist-info/top_level.txt
ipython_sql-0.5.0.dist-info/RECORD
