Metadata-Version: 2.1
Name: ipython-sql
Version: 0.5.0
Summary: RDBMS access via IPython
Home-page: https://github.com/catherinedevlin/ipython-sql
Author: Catherine Devlin
Author-email: catherine.devlin@gmail.com
License: MIT
Project-URL: Source, https://github.com/catherinedevlin/ipython-sql
Keywords: database ipython postgresql mysql
Classifier: Development Status :: 3 - Alpha
Classifier: Environment :: Console
Classifier: License :: OSI Approved :: MIT License
Classifier: Topic :: Database
Classifier: Topic :: Database :: Front-Ends
Classifier: Programming Language :: Python :: 3
License-File: LICENSE
